{
    "expertise": [
        {
        "title": "Advanced Digital Techniques",
        "description": "Inspiring tales of how our course transformed careers and businesses. Real examples of success in marketing.",
        "icon": "https://www.cci.ci/wp-content/uploads/2022/02/Globe.png"
        },
        {
        "title": "Real-World Case Studies",
        "description": "Learn firsthand about our course from those who have taken it. Discover their experiences and insights.",
        "icon": "https://www.cci.ci/wp-content/uploads/2022/02/argent.png"
        },
        {
        },
        {
        "title": "Insights from Experts",
        "description": "See the impact of our course through authentic testimonials and reviews from past students.",
        "icon": "https://www.cci.ci/wp-content/uploads/2022/02/Globe.png"
        },
        {
            "title": "Professional Certification",
            "description": "Insights from industry leaders who have applied our strategies to achieve marketing success.",
            "icon":  "https://www.cci.ci/wp-content/uploads/2022/02/terre.png"
            },
            {
            "title": "Networking Opportunities",
            "description": "Discover why our clients love our course and how it has helped them achieve their marketing goals.",
            "icon": "https://www.cci.ci/wp-content/uploads/2022/02/Graph.png"
            },
            {
            "title": "Personal Sessions",
            "description": "Discover how our course has benefited a diverse range of learners. Their stories showcase the course's impact.",
            "icon":"https://www.cci.ci/wp-content/uploads/2022/02/stand.png"
            }
    ]
}